Estructura/ha.v
module ha (output wire suma, output wire carry, input wire a, input wire b);
  xor xor1(suma, a, b);
  and and1(carry, a, b);
endmodule

Estructura/fa.v
module fa(output wire c_out, output wire sum, input wire a, input wire b, input wire c_in);

wire sum1;
wire carry1;
wire carry2;

ha ha1(sum1, carry1, a, b);
ha ha2(sum, carry2, sum1, c_in);

or or1(c_out, carry2, carry1);

endmodule

Estructura/ha_tb.v
`timescale 1 ns / 10ps

module fa_tb;

reg test_a, test_b, test_c_in;
wire test_suma, test_carry;

fa sumador1(test_carry, test_suma, test_a, test_b, test_c_in);

initial
begin
 $monitor("tiempo=%0d a=%b b=%b c_in=%b suma=%b acarreo=%b", $time, test_a, test_b, test_c_in, test_suma, test_carry);
    // Test vector 0
    test_a = 1'b0;
    test_b = 1'b0;
    test_c_in = 1'b0;
    #20;

    // Test vector 1
    test_a = 1'b0;
    test_b = 1'b1;
    test_c_in = 1'b0;
    #20;

    // Test vector 2
    test_a = 1'b1;
    test_b = 1'b0;
    test_c_in = 1'b0;
    #20;

    // Test vector 3
    test_a = 1'b1;
    test_b = 1'b1;
    test_c_in = 1'b0;
    #20;

    // Test vector 4 (with carry-in)
    test_a = 1'b0;
    test_b = 1'b0;
    test_c_in = 1'b1;
    #20;

    // Test vector 5 (with carry-in)
    test_a = 1'b1;
    test_b = 1'b0;
    test_c_in = 1'b1;
    #20;

    // Test vector 6 (with carry-in)
    test_a = 1'b0;
    test_b = 1'b1;
    test_c_in = 1'b1;
    #20;

    // Test vector 7 (with carry-in)
    test_a = 1'b1;
    test_b = 1'b1;
    test_c_in = 1'b1;
    #20;
 
 $finish; //fin simulacion
end

initial
begin
  $dumpfile("fa.vcd");
  $dumpvars;
end

endmodule

Estructura/fa.vcd
$date
	Mon Sep 30 18:45:29 2024
$end
$version
	Icarus Verilog
$end
$timescale
	10ps
$end
$scope module fa_tb $end
$var wire 1 ! test_suma $end
$var wire 1 " test_carry $end
$var reg 1 # test_a $end
$var reg 1 $ test_b $end
$var reg 1 % test_c_in $end
$scope module sumador1 $end
$var wire 1 # a $end
$var wire 1 $ b $end
$var wire 1 % c_in $end
$var wire 1 " c_out $end
$var wire 1 & sum1 $end
$var wire 1 ! sum $end
$var wire 1 ' carry2 $end
$var wire 1 ( carry1 $end
$scope module ha1 $end
$var wire 1 # a $end
$var wire 1 $ b $end
$var wire 1 ( carry $end
$var wire 1 & suma $end
$upscope $end
$scope module ha2 $end
$var wire 1 & a $end
$var wire 1 % b $end
$var wire 1 ' carry $end
$var wire 1 ! suma $end
$upscope $end
$upscope $end
$upscope $end
$enddefinitions $end
$comment Show the parameter values. $end
$dumpall
$end
#0
$dumpvars
0(
0'
0&
0%
0$
0#
0"
0!
$end
#2000
1!
1&
1$
#4000
0$
1#
#6000
0!
1"
0&
1(
1$
#8000
0"
1!
0(
1%
0$
0#
#10000
1"
0!
1'
1&
1#
#12000
1$
0#
#14000
1!
0'
0&
1(
1#
